LICENSE.txt
MANIFEST.in
README.rst
setup.py
mezzanine_tiles.egg-info/PKG-INFO
mezzanine_tiles.egg-info/SOURCES.txt
mezzanine_tiles.egg-info/dependency_links.txt
mezzanine_tiles.egg-info/top_level.txt
tiles/__init__.py
tiles/admin.py
tiles/models.py
tiles/tests.py
tiles/views.py