Metadata-Version: 1.1
Name: mezzanine-tiles
Version: 0.1.1
Summary: Add tiles (blocks, snippets) to mezzanine conten types.
Home-page: http://www.aip.pl/
Author: Adam Kochanowski
Author-email: aip@aip.pl
License: BSD License
Platform: UNKNOWN
Classifier: Environment :: Web Environment
Classifier: Framework :: Django
Classifier: Intended Audience :: Developers
Classifier: License :: OSI Approved :: BSD License
Classifier: Operating System :: OS Independent
Classifier: Programming Language :: Python
Classifier: Programming Language :: Python :: 2.7
Classifier: Topic :: Internet :: WWW/HTTP
Classifier: Topic :: Internet :: WWW/HTTP :: Dynamic Content
